init_problem/__init__.py
init_problem/__main__.py
init_problem/chapters.py
init_problem/choice_option.py
init_problem/main.py
init_problem/problem.py
init_problem-0.3.13.dist-info/METADATA
init_problem-0.3.13.dist-info/WHEEL
init_problem-0.3.13.dist-info/entry_points.txt
init_problem-0.3.13.dist-info/RECORD
