Metadata-Version: 2.1
Name: init-problem
Version: 0.3.13
Summary: Added link to launch the safari and locate to physics folder in gdrive.
Author: vaibhavblayer
Author-email: vaibhavblayer@gmail.com
Requires-Python: >=3.11,<4.0
Classifier: Programming Language :: Python :: 3
Classifier: Programming Language :: Python :: 3.11
Classifier: Programming Language :: Python :: 3.12
